{
  "home": {
    "title": "الى اين انت مسافر",
    "subtitle": "ابحث عن رحلاتك واحجزها بسهولة مع Jooland.",
    "search": "ابحث",
    "from": {
      "title": "ذهاب من",
      "value": "من"
    },
    "to": {
      "title": "ذهاب الى",
      "value": "الى"
    },
    "alert": "رجاءاً قم بملئ جميع الحقول",
    "flightsto": "رحلات الى",
    "setDate": "تعيين التاريخ",
    "oneway": "رحلة باتجاه واحد",
    "roundtrip": "جولة",
    "economy": "اقتصاد",
    "business": "عمل",
    "passengers": "ركاب",
    "adults": "الكبار",
    "adultsAge": "أكثر من 12 سنة",
    "children": "أطفال",
    "childrenAge": "2-12 سنة",
    "babies": "أطفال",
    "babiesAge": "0-2 سنة",
    "done": "منتهي",
    "whatoffers": "ماذا تقدم لك jooLand؟",
    "offers": [
      {
        "title": "البحث عن الرحلات الجوية",
        "description": "يمكننا توفير محرك بحث يسمح للعملاء بالعثور على رحلات جوية إلى وجهتهم المرجوة."
      },
      {
        "title": "حجز الرحلات عبر الإنترنت أو دون اتصال",
        "description": "نحن نساعد العملاء على حجز الرحلات مباشرة من خلال موقعنا الإلكتروني من خلال نظام الدفع الإلكتروني الخاص بنا."
      },
      {
        "title": "دعم العملاء",
        "description": "نحن نقدم دعم العملاء لمساعدة العملاء في أي مشاكل أو أسئلة قد تكون لديهم قبل رحلتهم أو خلالها أو بعدها."
      },
      {
        "title": "تنبيهات الطيران",
        "description": "يمكن أن يوفر موقعنا الإلكتروني تنبيهات بشأن التغييرات أو التأخير في الرحلات الجوية ، مما يضمن إطلاع العملاء على حالة رحلاتهم."
      }
    ],
    "bookflights": "احجز رحلات طيران في أي مكان في العالم",
    "bookflightscards": ["اسطنبول", "لندن", "باريس", "نيويورك"]
  },
  "nav": {
    "home": "الصفحة الرئيسية",
    "flights": "رحلات",
    "about": "حول"
  },
  "flights": {
    "title": "أفضل الرحلات المغادرة",
    "subtitle": "مرتبة على أساس السعر والراحة"
  }
}
